{
  "buildCommand" : {
    "command" : "preview",
    "style" : "xojit"
  },
  "buildDescriptionID" : "fe76d7a7246b3fd50af4ec5317da2001",
  "configuredTargets" : [
    {
      "guid" : "777b5fa28ab597fd23e99b4caf8023ecf15707f4970e67e51a44f8e8b93f056e"
    }
  ],
  "containerPath" : "/Users/linping/Desktop/活動歷/MyFirstProgram/Secalender/Secalender.xcodeproj",
  "continueBuildingAfterErrors" : true,
  "dependencyScope" : "workspace",
  "enableIndexBuildArena" : false,
  "hideShellScriptEnvironment" : false,
  "parameters" : {
    "action" : "build",
    "activeArchitecture" : "x86_64",
    "activeRunDestination" : {
      "disableOnlyActiveArch" : false,
      "platform" : "iphonesimulator",
      "sdk" : "iphonesimulator18.2",
      "sdkVariant" : "iphonesimulator",
      "supportedArchitectures" : [
        "x86_64"
      ],
      "targetArchitecture" : "x86_64"
    },
    "arenaInfo" : {
      "buildIntermediatesPath" : "/Users/linping/Desktop/活動歷/MyFirstProgram/Secalender/Build/Intermediates.noindex",
      "buildProductsPath" : "/Users/linping/Desktop/活動歷/MyFirstProgram/Secalender/Build/Products",
      "derivedDataPath" : "/Users/linping/Library/Developer/Xcode/DerivedData",
      "indexDataStoreFolderPath" : "/Users/linping/Library/Developer/Xcode/DerivedData/Secalender-gcbpvurnjjlaphbxrgdfdcthzclx/Index.noindex/DataStore",
      "indexEnableDataStore" : true,
      "indexPCHPath" : "/Users/linping/Library/Developer/Xcode/DerivedData/Secalender-gcbpvurnjjlaphbxrgdfdcthzclx/Index.noindex/PrecompiledHeaders",
      "pchPath" : "/Users/linping/Desktop/活動歷/MyFirstProgram/Secalender/Build/Intermediates.noindex/PrecompiledHeaders"
    },
    "configurationName" : "Debug",
    "overrides" : {
      "synthesized" : {
        "table" : {
          "ASSETCATALOG_FILTER_FOR_DEVICE_MODEL" : "iPhone17,1",
          "ASSETCATALOG_FILTER_FOR_DEVICE_OS_VERSION" : "18.2",
          "ASSETCATALOG_FILTER_FOR_THINNING_DEVICE_CONFIGURATION" : "iPhone17,1",
          "BUILD_ACTIVE_RESOURCES_ONLY" : "YES",
          "ENABLE_PREVIEWS" : "NO",
          "ENABLE_XOJIT_PREVIEWS" : "YES",
          "ONLY_ACTIVE_ARCH" : "YES",
          "TARGET_DEVICE_IDENTIFIER" : "B1D9D5C5-D66A-424C-BAF5-CF206D457F22",
          "TARGET_DEVICE_MODEL" : "iPhone17,1",
          "TARGET_DEVICE_OS_VERSION" : "18.2",
          "TARGET_DEVICE_PLATFORM_NAME" : "iphonesimulator"
        }
      }
    }
  },
  "schemeCommand" : "launch",
  "showNonLoggedProgress" : true,
  "useDryRun" : false,
  "useImplicitDependencies" : true,
  "useLegacyBuildLocations" : false,
  "useParallelTargets" : true
}